git/STpipe/stpipe/Findmarkers.py
git/STpipe/stpipe/QC.py
git/STpipe/stpipe/__init__.py
git/STpipe/stpipe/cluster.py
git/STpipe/stpipe/format.py
git/STpipe/stpipe/function.py
git/STpipe/stpipe/labeltransfer.py
git/STpipe/stpipe/plot.py
git/STpipe/stpipe/spatial_metacell.py
stpipe/Findmarkers.py
stpipe/QC.py
stpipe/__init__.py
stpipe/cluster.py
stpipe/format.py
stpipe/function.py
stpipe/labeltransfer.py
stpipe/plot.py
stpipe/spatial_metacell.py
STpipe_sc-0.0.5.dist-info/METADATA
STpipe_sc-0.0.5.dist-info/WHEEL
STpipe_sc-0.0.5.dist-info/top_level.txt
STpipe_sc-0.0.5.dist-info/RECORD
