Metadata-Version: 2.1
Name: STpipe-sc
Version: 0.0.5
Summary: STpipe is designed to analyze spatial transcriptomic data.
Home-page: https://github.com/mgy520/STpipe
Author: Mao Guangyao
License: MIT License
Requires-Python: ==3.8.*
Requires-Dist: rpy2 ==3.5.16
Requires-Dist: anndata2ri ==1.3.1
Requires-Dist: numpy ==1.21.6
Requires-Dist: diffxpy ==0.7.4
Requires-Dist: scipy ==1.10.1
Requires-Dist: pandas ==2.0.3
Requires-Dist: anndata ==0.9.2
Requires-Dist: shapely ==2.0.4
Requires-Dist: dask ==2023.5.0
Requires-Dist: numba ==0.57.1
Requires-Dist: pca ==2.0.5
Requires-Dist: openTSNE ==1.0.1
Requires-Dist: igraph ==0.11.4
Requires-Dist: sinfonia ==0.0.3
Requires-Dist: tangram-sc ==1.0.4
Requires-Dist: scanorama ==1.7.4
Requires-Dist: matplotlib ==3.7.5
Requires-Dist: seaborn ==0.13.2
Requires-Dist: adjustText ==1.1.1
Requires-Dist: scikit-learn ==1.3.2
Requires-Dist: scikit-misc ==0.1.4
Requires-Dist: scikit-image ==0.21.0
